rolo_tools/__init__.py
rolo_tools/logger.py
rolo_tools/manip.py
rolo_tools/secure_env.py
rolo_tools-0.0.7.dist-info/METADATA
rolo_tools-0.0.7.dist-info/WHEEL
rolo_tools-0.0.7.dist-info/licenses/LICENSE
rolo_tools-0.0.7.dist-info/RECORD
