Metadata-Version: 2.3
Name: rolo_tools
Version: 0.0.7
Summary: A collection of python tools for use in Windows Environments
Project-URL: Homepage, https://github.com/nullredirect/rolo_tools
Project-URL: Issues, https://github.com/nullredirect/rolo_tools/issues
Author-email: Rolando Teixeiro <rteixeiro@phantomsoftworks.com>
License-File: LICENSE
Classifier: License :: OSI Approved :: MIT License
Classifier: Operating System :: OS Independent
Classifier: Programming Language :: Python :: 3
Requires-Python: >=3.8
Requires-Dist: cryptography
